AUTHORS
ChangeLog
LICENSE
README.rst
__init__.py
requirements.txt
setup.cfg
setup.py
docs/Makefile
docs/make.bat
docs/source/conf.py
docs/source/index.rst
docs/source/modules.rst
spacetracktool/__init__.py
spacetracktool/operations.py
spacetracktool/spacetrackclient.py
spacetracktool.egg-info/PKG-INFO
spacetracktool.egg-info/SOURCES.txt
spacetracktool.egg-info/dependency_links.txt
spacetracktool.egg-info/pbr.json
spacetracktool.egg-info/requires.txt
spacetracktool.egg-info/top_level.txt
test/__init__.py
test/test_operations.py
test/test_space_track_client.py