Metadata-Version: 1.1
Name: spacetracktool
Version: 0.1.0b8
Summary: A Python API for querying space-track.org
Home-page: https://github.com/Engineero/spacetracktool
Author: Engineero
Author-email: engineerolabs@gmail.com
License: MIT
Keywords: space spacetrack elset tle satellite astronomy
Platform: UNKNOWN
Classifier: Development Status :: 4 - Beta
Classifier: Environment :: Console
Classifier: Intended Audience :: Developers
Classifier: Intended Audience :: Science/Research
Classifier: License :: OSI Approved :: MIT License
Classifier: Natural Language :: English
Classifier: Operating System :: OS Independent
Classifier: Programming Language :: Python
Classifier: Programming Language :: Python :: 3
Classifier: Programming Language :: Python :: 3.3
Classifier: Programming Language :: Python :: 3.4
Classifier: Programming Language :: Python :: 3.5
Classifier: Programming Language :: Python :: 3.6
Classifier: Topic :: Scientific/Engineering
Classifier: Topic :: Scientific/Engineering :: Astronomy
Classifier: Topic :: Utilities
